CHANGES.txt
LICENSE.txt
MANIFEST.in
README.md
setup.py
PyFi.egg-info/PKG-INFO
PyFi.egg-info/SOURCES.txt
PyFi.egg-info/dependency_links.txt
PyFi.egg-info/requires.txt
PyFi.egg-info/top_level.txt
bin/fifo
doc/fifo-datasets.1
doc/fifo-dtrace.1
doc/fifo-groupings.1
doc/fifo-hypervisors.1
doc/fifo-ipranges.1
doc/fifo-networks.1
doc/fifo-orgs.1
doc/fifo-packages.1
doc/fifo-roles.1
doc/fifo-users.1
doc/fifo-vmconfig.5
doc/fifo-vms.1
doc/fifo.1
doc/install.sh
fifo/__init__.py
fifo/helper.py
fifo/api/__init__.py
fifo/api/dataset.py
fifo/api/dtrace.py
fifo/api/groupings.py
fifo/api/hypervisor.py
fifo/api/iprange.py
fifo/api/network.py
fifo/api/org.py
fifo/api/package.py
fifo/api/role.py
fifo/api/user.py
fifo/api/vm.py
fifo/api/wiggle.py