Metadata-Version: 1.1
Name: PyFi
Version: 0.2.9
Summary: Project FiFo API implementation and console client.
Home-page: https://project-fifo.net
Author: Heinz N. Gies
Author-email: heinz@licenser.net
License: CDDL
Platform: UNKNOWN
Classifier: Development Status :: 4 - Beta
Classifier: Environment :: Console
Classifier: Environment :: Web Environment
Classifier: Intended Audience :: Developers
Classifier: Intended Audience :: System Administrators
Classifier: License :: OSI Approved
Classifier: Operating System :: OS Independent
Classifier: Operating System :: Unix
Classifier: Operating System :: POSIX
Classifier: Programming Language :: Python
Classifier: Topic :: Internet
Classifier: Topic :: System :: Systems Administration
Classifier: Topic :: Utilities
